tabtosql
