Metadata-Version: 1.1
Name: tabtosql
Version: 1.0.2
Summary: Tableau Workbook SQL Extract Tool
Home-page: https://github.com/LeviKanwischer/tabtosql
Author: Levi Kanwischer
Author-email: levi@kanwischer.me
License: MIT
Keywords: Tableau sql
Platform: UNKNOWN
Classifier: Development Status :: 5 - Production/Stable
Classifier: Environment :: Console
Classifier: Intended Audience :: Developers
Classifier: License :: OSI Approved :: MIT License
Classifier: Natural Language :: English
Classifier: Operating System :: OS Independent
Classifier: Programming Language :: Python
Classifier: Programming Language :: Python :: 2
Classifier: Programming Language :: Python :: 2.6
Classifier: Programming Language :: Python :: 2.7
Classifier: Programming Language :: Python :: 3
Classifier: Programming Language :: Python :: 3.4
Classifier: Programming Language :: Python :: 3.5
Classifier: Topic :: Utilities
